timecapsule/__init__.py
timecapsule/timecapsule.py
timecapsule/zone_manager.py
timecapsule-0.1.2.dist-info/METADATA
timecapsule-0.1.2.dist-info/WHEEL
timecapsule-0.1.2.dist-info/RECORD
