Metadata-Version: 2.3
Name: timecapsule
Version: 0.1.2
Summary: Human-friendly datetime handling for Python
Author: Danny Stewart
Author-email: danny@stewart.cc
Requires-Python: >=3.12
Classifier: Programming Language :: Python :: 3
Classifier: Programming Language :: Python :: 3.12
Classifier: Programming Language :: Python :: 3.13
Requires-Dist: devpkg (>=0.2.0)
Requires-Dist: python-dateutil (>=2.9.0.post0)
Requires-Dist: tzlocal (>=5.3.1)
